casbin_sqlobject_adapter/__init__.py
casbin_sqlobject_adapter/adapter.py
casbin_sqlobject_adapter-0.2.0.dist-info/LICENSE
casbin_sqlobject_adapter-0.2.0.dist-info/METADATA
casbin_sqlobject_adapter-0.2.0.dist-info/WHEEL
casbin_sqlobject_adapter-0.2.0.dist-info/top_level.txt
casbin_sqlobject_adapter-0.2.0.dist-info/RECORD
